pylfit/__init__.py
pylfit/utils.py
pylfit/algorithms/__init__.py
pylfit/algorithms/acedia.py
pylfit/algorithms/algorithm.py
pylfit/algorithms/bruteForce.py
pylfit/algorithms/gula.py
pylfit/algorithms/lfkt.py
pylfit/algorithms/lust.py
pylfit/algorithms/pride.py
pylfit/algorithms/probalizer.py
pylfit/algorithms/synchronizer.py
pylfit/datasets/__init__.py
pylfit/datasets/continuousStateTransitionsDataset.py
pylfit/datasets/dataset.py
pylfit/datasets/discreteStateTransitionsDataset.py
pylfit/models/__init__.py
pylfit/models/cdmvlp.py
pylfit/models/clp.py
pylfit/models/dmvlp.py
pylfit/models/model.py
pylfit/models/pdmvlp.py
pylfit/models/wdmvlp.py
pylfit/objects/__init__.py
pylfit/objects/atom.py
pylfit/objects/continuum.py
pylfit/objects/continuumRule.py
pylfit/objects/legacyAtom.py
pylfit/objects/rule.py
pylfit/postprocessing/__init__.py
pylfit/postprocessing/counterfactuals.py
pylfit/postprocessing/metrics.py
pylfit/preprocessing/__init__.py
pylfit/preprocessing/boolean_network.py
pylfit/preprocessing/tabular_dataset.py
pylfit/semantics/__init__.py
pylfit/semantics/asynchronous.py
pylfit/semantics/general.py
pylfit/semantics/semantics.py
pylfit/semantics/synchronous.py
pylfit/semantics/synchronousConstrained.py
pylfit-0.5.1.dist-info/LICENSE
pylfit-0.5.1.dist-info/METADATA
pylfit-0.5.1.dist-info/WHEEL
pylfit-0.5.1.dist-info/top_level.txt
pylfit-0.5.1.dist-info/RECORD
