Metadata-Version: 2.1
Name: pylfit
Version: 0.5.1
Summary: LFIT algorithms package
Home-page: https://github.com/Tony-sama/pylfit
Author: Tony Ribeiro
Author-email: tonyribeiro.research.aca@gmail.com
Classifier: Programming Language :: Python :: 3
Classifier: License :: OSI Approved :: GNU General Public License v3 (GPLv3)
Classifier: Operating System :: OS Independent
Requires-Python: >=3.6
License-File: LICENSE
